{
    "identityPoolName": "landing59ee0f62_identitypool_59ee0f62",
    "allowUnauthenticatedIdentities": false,
    "resourceNameTruncated": "landin59ee0f62",
    "userPoolName": "landing59ee0f62_userpool_59ee0f62",
    "autoVerifiedAttributes": [
        "email"
    ],
    "mfaConfiguration": "OFF",
    "mfaTypes": [
        "SMS Text Message"
    ],
    "smsAuthenticationMessage": "Your authentication code is {####}",
    "smsVerificationMessage": "Your verification code is {####}",
    "emailVerificationSubject": "Your verification code",
    "emailVerificationMessage": "Your verification code is {####}",
    "defaultPasswordPolicy": false,
    "passwordPolicyMinLength": 8,
    "passwordPolicyCharacters": [],
    "requiredAttributes": [
        "email"
    ],
    "aliasAttributes": [
        "email"
    ],
    "userpoolClientGenerateSecret": false,
    "userpoolClientRefreshTokenValidity": 30,
    "userpoolClientWriteAttributes": [
        "email"
    ],
    "userpoolClientReadAttributes": [
        "email"
    ],
    "userpoolClientLambdaRole": "landin59ee0f62_userpoolclient_lambda_role",
    "userpoolClientSetAttributes": false,
    "sharedId": "59ee0f62",
    "resourceName": "landing59ee0f62",
    "authSelections": "identityPoolAndUserPool",
    "authRoleArn": {
        "Fn::GetAtt": [
            "AuthRole",
            "Arn"
        ]
    },
    "unauthRoleArn": {
        "Fn::GetAtt": [
            "UnauthRole",
            "Arn"
        ]
    },
    "useDefault": "manual",
    "userPoolGroupList": [],
    "serviceName": "Cognito",
    "usernameCaseSensitive": false,
    "dependsOn": [
        {
            "category": "function",
            "resourceName": "landing59ee0f62PreSignup",
            "triggerProvider": "Cognito",
            "attributes": [
                "Arn",
                "Name"
            ]
        }
    ],
    "thirdPartyAuth": false,
    "userPoolGroups": false,
    "adminQueries": false,
    "triggers": "{\n  \"PreSignup\": [\n    \"custom\"\n  ]\n}",
    "hostedUI": false,
    "parentStack": {
        "Ref": "AWS::StackId"
    },
    "authTriggerConnections": "[\n  {\n    \"triggerType\": \"PreSignUp\",\n    \"lambdaFunctionName\": \"landing59ee0f62PreSignup\"\n  }\n]",
    "breakCircularDependency": true,
    "permissions": [],
    "authProviders": []
}